sphinx_watermark/__init__.py
sphinx_watermark/fonts/Anton.ttf
sphinx_watermark/fonts/Gluten.ttf
sphinx_watermark/fonts/KodeMono.ttf
sphinx_watermark/fonts/LICENSE_APACHE2.txt
sphinx_watermark/fonts/LICENSE_OFL.txt
sphinx_watermark/fonts/README.txt
sphinx_watermark/fonts/RobotoMono.ttf
sphinx_watermark/fonts/RubikDistressed.ttf
sphinx_watermark/fonts/ShantellSans.ttf
sphinx_watermark-2.0.0.dist-info/LICENSE
sphinx_watermark-2.0.0.dist-info/METADATA
sphinx_watermark-2.0.0.dist-info/WHEEL
sphinx_watermark-2.0.0.dist-info/top_level.txt
sphinx_watermark-2.0.0.dist-info/RECORD
