Metadata-Version: 2.1
Name: sphinx-watermark
Version: 2.0.0
Summary: A Sphinx extension that enables watermarks for HTML output.
Home-page: https://github.com/JoKneeMo/sphinx-watermark
Author: JoKneeMo <https://github.com/JoKneeMo>
Author-email: 421625+JoKneeMo@users.noreply.github.com
License: GPLv3
Project-URL: repository, https://github.com/JoKneeMo/sphinx-watermark
Project-URL: homepage, https://jokneemo.github.io/sphinx-watermark
Project-URL: documentation, https://jokneemo.github.io/sphinx-watermark
Project-URL: issues, https://github.com/JoKneeMo/sphinx-watermark/issues
Keywords: Python3,Sphinx,Extension,watermark
Platform: any
Classifier: Development Status :: 5 - Production/Stable
Classifier: Intended Audience :: Developers
Classifier: Topic :: Documentation :: Sphinx
Classifier: Framework :: Sphinx :: Extension
Classifier: License :: OSI Approved :: GNU General Public License v3 (GPLv3)
Classifier: Programming Language :: Python
Classifier: Programming Language :: Python :: 3
Classifier: Programming Language :: Python :: 3.7
Classifier: Programming Language :: Python :: 3.8
Classifier: Programming Language :: Python :: 3.9
Classifier: Programming Language :: Python :: 3.10
Classifier: Programming Language :: Python :: 3.11
Requires-Python: >=3
License-File: LICENSE
Requires-Dist: Pillow >=6.0.0
Requires-Dist: sphinx >=2.0.0
